slightly_better_types/__init__.py
slightly_better_types/function.py
slightly_better_types/handlers.py
slightly_better_types/parameter.py
slightly_better_types/utils.py
tests/__init__.py
tests/test_function.py
tests/test_handlers.py
tests/test_parameter.py
slightly_better_types-1.0.0.dist-info/LICENSE
slightly_better_types-1.0.0.dist-info/METADATA
slightly_better_types-1.0.0.dist-info/WHEEL
slightly_better_types-1.0.0.dist-info/top_level.txt
slightly_better_types-1.0.0.dist-info/RECORD
