Metadata-Version: 2.1
Name: slightly-better-types
Version: 1.0.0
Summary: Improved abstraction for dealing with union and named types.
Home-page: https://github.com/slightly-better-python/slightly-better-types
Author: Peter Wensel
Author-email: pwensel@gmail.com
License: UNKNOWN
Platform: UNKNOWN
Classifier: Programming Language :: Python :: 3
Classifier: License :: OSI Approved :: MIT License
Classifier: Operating System :: OS Independent
Requires-Python: >=3.9
License-File: LICENSE
